LICENSE
MANIFEST.in
README.md
README.txt
readme.md
setup.py
SkyFish.egg-info/PKG-INFO
SkyFish.egg-info/SOURCES.txt
SkyFish.egg-info/dependency_links.txt
SkyFish.egg-info/not-zip-safe
SkyFish.egg-info/requires.txt
SkyFish.egg-info/top_level.txt
skyfish/.skyfish.py.swp
skyfish/__init__.py
skyfish/__init__.pyc
skyfish/skyfish.py
skyfish/skyfish.pyc
skyfish/models/__init__.py
skyfish/models/config.py
skyfish/models/product_data.py
skyfish/models/response.py
tests/__init__.py
tests/__init__.pyc
tests/config_test.py
tests/config_test.pyc
tests/product_data_test.py
tests/product_data_test.pyc
tests/response_test.py
tests/response_test.pyc
tests/skyfish_test.py
tests/skyfish_test.pyc