Metadata-Version: 1.0
Name: SkyFish
Version: 0.3.4
Summary: Official Skyfish Inventory Integration SDK for Merchants
Home-page: https://github.com/coralhq/skyfish-py-sdk
Author: Fauzan Emmerling
Author-email: erich@emfeld.com
License: MIT
Platform: UNKNOWN
